sfusion/__init__.py
sfusion/kalman/EKFGPSAccelerometerGyro2D.py
sfusion/kalman/EKFGPSAccelerometerGyro3D.py
sfusion/kalman/EKFGPSPolar2D.py
sfusion/kalman/LinearKFGPS1D.py
sfusion/kalman/LinearKFGPS2D.py
sfusion/kalman/LinearKFGPS3D.py
sfusion/kalman/LinearKFGPSAccelerometer1D.py
sfusion/kalman/LinearKFGPSAccelerometer2D.py
sfusion/kalman/LinearKFGPSAccelerometer3D.py
sfusion/kalman/LinearKFGPSAccelerometerGyro2D.py
sfusion/kalman/LinearKFGPSAccelerometerGyro3D.py
sfusion/kalman/LinearKFGPSGyro2D.py
sfusion/kalman/UKFGPSAccelerometerGyro2D.py
sfusion/kalman/UKFGPSAccelerometerGyro3D.py
sfusion/kalman/__init__.py
sfusion/particle/PFGPSAccelerometerGyro2D.py
sfusion/particle/__init__.py
rtls_fusion-0.1.6.dist-info/LICENCE
rtls_fusion-0.1.6.dist-info/METADATA
rtls_fusion-0.1.6.dist-info/WHEEL
rtls_fusion-0.1.6.dist-info/top_level.txt
rtls_fusion-0.1.6.dist-info/RECORD
